LICENSE
MANIFEST.in
setup.py
hunters/__init__.py
hunters/atomic.py
hunters/benchmark.py
hunters/browser.py
hunters/chrome.py
hunters/config.py
hunters/constant.py
hunters/cookie.py
hunters/core.py
hunters/defaults.py
hunters/exceptions.py
hunters/pool.py
hunters/queues.py
hunters/spider.py
hunters/utils.py
hunters.egg-info/PKG-INFO
hunters.egg-info/SOURCES.txt
hunters.egg-info/dependency_links.txt
hunters.egg-info/requires.txt
hunters.egg-info/top_level.txt
hunters/factory/__init__.py
hunters/factory/browser_factory.py
hunters/util/__init__.py
hunters/util/file_util.py
hunters/util/htmlutil.py
hunters/util/socket_util.py
hunters/util/timerutil.py
hunters/util/xmlutil.py
test/test_atomic.py
test/test_browser.py
test/test_chromepool.py
test/test_code.py
test/test_core.py
test/test_core_view.py
test/test_foreverthreadpool.py
test/test_get_real_url.py
test/test_itertool.py
test/test_multichrome.py
test/test_phantomjs.py
test/test_regex.py
test/test_viewbrowser.py