Metadata-Version: 1.0
Name: hunters
Version: 2.0.14
Summary: A spider automation framework, provide uniform API to use chrome Dev Protocol and requests
Home-page: https://github.com/LoginQin/hunters
Author: Qin Wei (ChineseTiger)
Author-email: imqinwei@qq.com
License: Apache License, Version 2.0
Keywords: hunters spider headless crawlers screenshot
Platform: UNKNOWN
